dynsight/__init__.py
dynsight/analysis.py
dynsight/data_processing.py
dynsight/descriptors.py
dynsight/hdf5er.py
dynsight/lens.py
dynsight/logs.py
dynsight/onion.py
dynsight/py.typed
dynsight/soap.py
dynsight/track.py
dynsight/trajectory.py
dynsight/utilities.py
dynsight/vision.py
dynsight/_internal/__init__.py
dynsight/_internal/logs.py
dynsight/_internal/analysis/__init__.py
dynsight/_internal/analysis/entropy.py
dynsight/_internal/analysis/rdf.py
dynsight/_internal/analysis/spatial_average.py
dynsight/_internal/analysis/time_correlations.py
dynsight/_internal/data_processing/__init__.py
dynsight/_internal/data_processing/classify.py
dynsight/_internal/data_processing/distances.py
dynsight/_internal/descriptors/__init__.py
dynsight/_internal/descriptors/misc.py
dynsight/_internal/descriptors/tica.py
dynsight/_internal/hdf5er/__init__.py
dynsight/_internal/hdf5er/from_hdf5.py
dynsight/_internal/hdf5er/to_hdf5.py
dynsight/_internal/lens/__init__.py
dynsight/_internal/lens/lens.py
dynsight/_internal/onion/__init__.py
dynsight/_internal/soapify/__init__.py
dynsight/_internal/soapify/saponify.py
dynsight/_internal/timesoap/__init__.py
dynsight/_internal/timesoap/timesoap.py
dynsight/_internal/track/__init__.py
dynsight/_internal/track/track.py
dynsight/_internal/trajectory/__init__.py
dynsight/_internal/trajectory/cluster_insight.py
dynsight/_internal/trajectory/insight.py
dynsight/_internal/trajectory/trajectory.py
dynsight/_internal/utilities/__init__.py
dynsight/_internal/utilities/utilities.py
dynsight/_internal/vision/__init__.py
dynsight/_internal/vision/label_tool.py
dynsight/_internal/vision/vision.py
dynsight/_internal/vision/label_tool/index.html
dynsight/_internal/vision/label_tool/script.js
dynsight/_internal/vision/label_tool/styles.css
dynsight-2025.8.27.dist-info/licenses/LICENSE
dynsight-2025.8.27.dist-info/METADATA
dynsight-2025.8.27.dist-info/WHEEL
dynsight-2025.8.27.dist-info/entry_points.txt
dynsight-2025.8.27.dist-info/top_level.txt
dynsight-2025.8.27.dist-info/RECORD
