Metadata-Version: 2.4
Name: dynsight
Version: 2025.8.27
Summary: Simplifies analysis of simulation and experimental trajectories.
Maintainer-email: Andrew Tarzia <andrew.tarzia@gmail.com>, Matteo Becchi <bechmath@gmail.com>, Simone Martino <s.martino0898@gmail.com>
Project-URL: github, https://github.com/GMPavanLab/dynsight
Project-URL: documentation, https://dynsight.readthedocs.io/en/latest/
Requires-Python: >=3.8
License-File: LICENSE
Requires-Dist: numpy
Requires-Dist: dscribe
Requires-Dist: tropea-clustering
Requires-Dist: MDAnalysis
Requires-Dist: PyYAML
Requires-Dist: trackpy
Requires-Dist: ultralytics
Requires-Dist: deeptime
Provides-Extra: dev
Requires-Dist: ruff; extra == "dev"
Requires-Dist: mypy; extra == "dev"
Requires-Dist: pytest; extra == "dev"
Requires-Dist: pytest-cov; extra == "dev"
Requires-Dist: sphinx; extra == "dev"
Requires-Dist: sphinx-copybutton; extra == "dev"
Requires-Dist: build; extra == "dev"
Requires-Dist: twine; extra == "dev"
Requires-Dist: furo; extra == "dev"
Requires-Dist: numba; extra == "dev"
Dynamic: license-file
